AlzScPred/Diagnosis.py
AlzScPred/Model_Selection.py
AlzScPred/PredictionModule.py
AlzScPred/__init__.py
AlzScPred/preprocessing.py
AlzScPred/Model/__init__.py
AlzScPred/Model/keras_metadata.pb
AlzScPred/Model/saved_model.pb
AlzScPred/Model/assets/__init__.py
AlzScPred/Model/variables/__init__.py
AlzScPred/Model/variables/variables.data-00000-of-00001
AlzScPred/Model/variables/variables.index
AlzScPred-0.0.3.dist-info/LICENSE.txt
AlzScPred-0.0.3.dist-info/METADATA
AlzScPred-0.0.3.dist-info/WHEEL
AlzScPred-0.0.3.dist-info/top_level.txt
AlzScPred-0.0.3.dist-info/RECORD
