Metadata-Version: 2.1
Name: AlzScPred
Version: 0.0.3
Summary: A python based tool for prediction patient diagnosis i.e. (Alzheimer or Healthy) from single cell data.
Author: Aman Srivastava and Akanksha Jarwal
Author-email: <aman20333@iiitd.ac.in>
License: UNKNOWN
Keywords: python,Alzheimers,Diagnosis,Single cell,Genomics
Platform: UNKNOWN
Classifier: Development Status :: 1 - Planning
Classifier: Intended Audience :: Developers
Classifier: Programming Language :: Python :: 3
Classifier: Operating System :: Unix
Classifier: Operating System :: MacOS :: MacOS X
Classifier: Operating System :: Microsoft :: Windows
Requires-Dist: pandas
Requires-Dist: numpy
Requires-Dist: tensorflow
Requires-Dist: keras
